{
  "Sections": [
    {
      "Order": 2,
      "Lable": "Electric Service",
      "FontSize": 30,
      "Color": "#00294A",
      "IsItalic": false,
      "IsBreakdown": false,
      "SectionType": "Service",
      "ServiceType": "Electric",
      "Section_Level1s": [
        {
          "Order": 1,
          "Value": "5100007621",
          "FontSize": 0,
          "IsItalic": false,
          "IsBreakdown": false,
          "SectionType": "Config"
        },
        {
          "Order": 2,
          "FontSize": 0,
          "IsItalic": false,
          "IsBreakdown": false,
          "SectionType": "Charge_Group",
          "Section_Level2s": [
            {
              "Order": 1,
              "Value": "Basic Service Charge",
              "FontSize": 20,
              "Color": "#000000",
              "IsItalic": false,
              "IsBreakdown": false,
              "SectionType": "Charge"
            },
            {
              "Order": 4,
              "Value": "$33.24",
              "FontSize": 20,
              "Color": "#000000",
              "IsItalic": false,
              "IsBreakdown": false,
              "SectionType": "Charge"
            }
          ]
        },
        {
          "Order": 2,
          "FontSize": 0,
          "IsItalic": false,
          "IsBreakdown": false,
          "SectionType": "Charge_Group",
          "Section_Level2s": [
            {
              "Order": 1,
              "Value": "Billing Demand Charge",
              "ToolTip": "Billing Demand Charge\n\n",
              "FontSize": 20,
              "Color": "#000000",
              "IsItalic": false,
              "IsBreakdown": false,
              "SectionType": "Charge"
            },
            {
              "Order": 2,
              "Value": "30 kW",
              "FontSize": 18,
              "Color": "#005FAA",
              "IsItalic": true,
              "IsBreakdown": false,
              "SectionType": "Charge"
            },
            {
              "Order": 3,
              "Value": "@ $3.46000/kW",
              "FontSize": 18,
              "Color": "#005FAA",
              "IsItalic": true,
              "IsBreakdown": false,
              "SectionType": "Charge"
            },
            {
              "Order": 4,
              "Value": "$103.80",
              "FontSize": 20,
              "Color": "#000000",
              "IsItalic": false,
              "IsBreakdown": false,
              "SectionType": "Charge"
            }
          ]
        },
        {
          "Order": 2,
          "FontSize": 0,
          "IsItalic": false,
          "IsBreakdown": false,
          "SectionType": "Charge_Group",
          "Section_Level2s": [
            {
              "Order": 1,
              "Value": "Peak Demand Charge",
              "FontSize": 20,
              "Color": "#000000",
              "IsItalic": false,
              "IsBreakdown": false,
              "SectionType": "Charge"
            },
            {
              "Order": 2,
              "Value": "30 kW",
              "FontSize": 18,
              "Color": "#005FAA",
              "IsItalic": true,
              "IsBreakdown": false,
              "SectionType": "Charge"
            },
            {
              "Order": 3,
              "Value": "@ $6.79000/kW",
              "FontSize": 18,
              "Color": "#005FAA",
              "IsItalic": true,
              "IsBreakdown": false,
              "SectionType": "Charge"
            },
            {
              "Order": 4,
              "Value": "$203.70",
              "FontSize": 20,
              "Color": "#000000",
              "IsItalic": false,
              "IsBreakdown": false,
              "SectionType": "Charge"
            }
          ]
        },
        {
          "Order": 2,
          "FontSize": 0,
          "IsItalic": false,
          "IsBreakdown": false,
          "SectionType": "Charge_Group",
          "Section_Level2s": [
            {
              "Order": 1,
              "Value": "Energy Charge - On Peak",
              "FontSize": 20,
              "Color": "#000000",
              "IsItalic": false,
              "IsBreakdown": false,
              "SectionType": "Charge"
            },
            {
              "Order": 2,
              "Value": "4,320 kWh",
              "FontSize": 18,
              "Color": "#005FAA",
              "IsItalic": true,
              "IsBreakdown": false,
              "SectionType": "Charge"
            },
            {
              "Order": 3,
              "Value": "@ $0.03211/kWh",
              "FontSize": 18,
              "Color": "#005FAA",
              "IsItalic": true,
              "IsBreakdown": false,
              "SectionType": "Charge"
            },
            {
              "Order": 4,
              "Value": "$138.72",
              "FontSize": 20,
              "Color": "#000000",
              "IsItalic": false,
              "IsBreakdown": false,
              "SectionType": "Charge"
            }
          ]
        },
        {
          "Order": 2,
          "FontSize": 0,
          "IsItalic": false,
          "IsBreakdown": false,
          "SectionType": "Charge_Group",
          "Section_Level2s": [
            {
              "Order": 1,
              "Value": "Energy Charge - Off Peak",
              "FontSize": 20,
              "Color": "#000000",
              "IsItalic": false,
              "IsBreakdown": false,
              "SectionType": "Charge"
            },
            {
              "Order": 2,
              "Value": "9,120 kWh",
              "FontSize": 18,
              "Color": "#005FAA",
              "IsItalic": true,
              "IsBreakdown": false,
              "SectionType": "Charge"
            },
            {
              "Order": 3,
              "Value": "@ $0.01159/kWh",
              "FontSize": 18,
              "Color": "#005FAA",
              "IsItalic": true,
              "IsBreakdown": false,
              "SectionType": "Charge"
            },
            {
              "Order": 4,
              "Value": "$105.70",
              "FontSize": 20,
              "Color": "#000000",
              "IsItalic": false,
              "IsBreakdown": false,
              "SectionType": "Charge"
            }
          ]
        },
        {
          "Order": 2,
          "FontSize": 0,
          "IsItalic": false,
          "IsBreakdown": false,
          "SectionType": "Charge_Group",
          "Section_Level2s": [
            {
              "Order": 1,
              "Value": "Fuel Charge",
              "ToolTip": "Fuel Charge\n\n",
              "FontSize": 20,
              "Color": "#000000",
              "IsItalic": false,
              "IsBreakdown": false,
              "SectionType": "Charge"
            }
          ]
        },
        {
          "Order": 2,
          "FontSize": 0,
          "IsItalic": false,
          "IsBreakdown": false,
          "SectionType": "Charge_Group",
          "Section_Level2s": [
            {
              "Order": 1,
              "Value": "On-Peak",
              "FontSize": 20,
              "Color": "#000000",
              "IsItalic": false,
              "IsBreakdown": true,
              "SectionType": "Charge"
            },
            {
              "Order": 2,
              "Value": "4,320 kWh",
              "FontSize": 18,
              "Color": "#005FAA",
              "IsItalic": true,
              "IsBreakdown": false,
              "SectionType": "Charge"
            },
            {
              "Order": 3,
              "Value": "@ $0.03166/kWh",
              "FontSize": 18,
              "Color": "#005FAA",
              "IsItalic": true,
              "IsBreakdown": false,
              "SectionType": "Charge"
            },
            {
              "Order": 4,
              "Value": "$136.77",
              "FontSize": 20,
              "Color": "#000000",
              "IsItalic": false,
              "IsBreakdown": false,
              "SectionType": "Charge"
            }
          ]
        },
        {
          "Order": 2,
          "FontSize": 0,
          "IsItalic": false,
          "IsBreakdown": false,
          "SectionType": "Charge_Group",
          "Section_Level2s": [
            {
              "Order": 1,
              "Value": "Off-Peak",
              "FontSize": 20,
              "Color": "#000000",
              "IsItalic": false,
              "IsBreakdown": true,
              "SectionType": "Charge"
            },
            {
              "Order": 2,
              "Value": "9,120 kWh",
              "FontSize": 18,
              "Color": "#005FAA",
              "IsItalic": true,
              "IsBreakdown": false,
              "SectionType": "Charge"
            },
            {
              "Order": 3,
              "Value": "@ $0.02865/kWh",
              "FontSize": 18,
              "Color": "#005FAA",
              "IsItalic": true,
              "IsBreakdown": false,
              "SectionType": "Charge"
            },
            {
              "Order": 4,
              "Value": "$261.29",
              "FontSize": 20,
              "Color": "#000000",
              "IsItalic": false,
              "IsBreakdown": false,
              "SectionType": "Charge"
            }
          ]
        },
        {
          "Order": 2,
          "FontSize": 0,
          "IsItalic": false,
          "IsBreakdown": false,
          "SectionType": "Charge_Group",
          "Section_Level2s": [
            {
              "Order": 1,
              "Value": "Capacity Charge",
              "ToolTip": "Capacity Charge",
              "FontSize": 20,
              "Color": "#000000",
              "IsItalic": false,
              "IsBreakdown": false,
              "SectionType": "Charge"
            },
            {
              "Order": 2,
              "Value": "30 kW",
              "FontSize": 18,
              "Color": "#005FAA",
              "IsItalic": true,
              "IsBreakdown": false,
              "SectionType": "Charge"
            },
            {
              "Order": 3,
              "Value": "@ $0.27000/kW",
              "FontSize": 18,
              "Color": "#005FAA",
              "IsItalic": true,
              "IsBreakdown": false,
              "SectionType": "Charge"
            },
            {
              "Order": 4,
              "Value": "$8.10",
              "FontSize": 20,
              "Color": "#000000",
              "IsItalic": false,
              "IsBreakdown": false,
              "SectionType": "Charge"
            }
          ]
        },
        {
          "Order": 2,
          "FontSize": 0,
          "IsItalic": false,
          "IsBreakdown": false,
          "SectionType": "Charge_Group",
          "Section_Level2s": [
            {
              "Order": 1,
              "Value": "Energy Conservation Charge",
              "ToolTip": "Energy Conservation Charge\n\n",
              "FontSize": 20,
              "Color": "#000000",
              "IsItalic": false,
              "IsBreakdown": false,
              "SectionType": "Charge"
            },
            {
              "Order": 2,
              "Value": "30 kW",
              "FontSize": 18,
              "Color": "#005FAA",
              "IsItalic": true,
              "IsBreakdown": false,
              "SectionType": "Charge"
            },
            {
              "Order": 3,
              "Value": "@ $0.77000/kW",
              "FontSize": 18,
              "Color": "#005FAA",
              "IsItalic": true,
              "IsBreakdown": false,
              "SectionType": "Charge"
            },
            {
              "Order": 4,
              "Value": "$23.10",
              "FontSize": 20,
              "Color": "#000000",
              "IsItalic": false,
              "IsBreakdown": false,
              "SectionType": "Charge"
            }
          ]
        },
        {
          "Order": 2,
          "FontSize": 0,
          "IsItalic": false,
          "IsBreakdown": false,
          "SectionType": "Charge_Group",
          "Section_Level2s": [
            {
              "Order": 1,
              "Value": "Environmental Cost Recovery",
              "ToolTip": "Environmental Cost Recovery",
              "FontSize": 20,
              "Color": "#000000",
              "IsItalic": false,
              "IsBreakdown": false,
              "SectionType": "Charge"
            },
            {
              "Order": 2,
              "Value": "13,440 kWh",
              "FontSize": 18,
              "Color": "#005FAA",
              "IsItalic": true,
              "IsBreakdown": false,
              "SectionType": "Charge"
            },
            {
              "Order": 3,
              "Value": "@ $0.00386/kWh",
              "FontSize": 18,
              "Color": "#005FAA",
              "IsItalic": true,
              "IsBreakdown": false,
              "SectionType": "Charge"
            },
            {
              "Order": 4,
              "Value": "$51.88",
              "FontSize": 20,
              "Color": "#000000",
              "IsItalic": false,
              "IsBreakdown": false,
              "SectionType": "Charge"
            }
          ]
        },
        {
          "Order": 2,
          "FontSize": 0,
          "IsItalic": false,
          "IsBreakdown": false,
          "SectionType": "Charge_Group",
          "Section_Level2s": [
            {
              "Order": 1,
              "Value": "Florida Gross Receipt Tax",
              "ToolTip": "Florida Gross Receipt Tax",
              "FontSize": 20,
              "Color": "#000000",
              "IsItalic": false,
              "IsBreakdown": false,
              "SectionType": "Charge"
            },
            {
              "Order": 4,
              "Value": "$27.34",
              "FontSize": 20,
              "Color": "#000000",
              "IsItalic": false,
              "IsBreakdown": false,
              "SectionType": "Charge"
            }
          ]
        },
        {
          "Order": 3,
          "Lable": "Electric Charges Subtotal",
          "Value": "$1,093.64",
          "FontSize": 20,
          "Color": "#005FAA",
          "IsItalic": false,
          "IsBreakdown": false,
          "SectionType": "Total"
        }
      ]
    },
    {
      "Order": 3,
      "Lable": "Total Current Charges",
      "Value": "$2,023.06",
      "FontSize": 35,
      "Color": "#005FAA",
      "IsItalic": false,
      "IsBreakdown": false,
      "SectionType": "InvoiceTotal"
    }
  ]
}